mkdocs_test/__init__.py
mkdocs_test/common.py
mkdocs_test/lorem.py
mkdocs_test/plugin.py
mkdocs_test-0.6.0.dist-info/licenses/LICENSE
test/test_ad_hoc.py
test/test_simple.py
test/test_various.py
test/advanced/__init__.py
test/advanced/test_advanced.py
test/alter_markdown/__init__.py
test/alter_markdown/hooks.py
test/alter_markdown/test_site.py
test/simple/__init__.py
test/simple/test_site.py
mkdocs_test-0.6.0.dist-info/METADATA
mkdocs_test-0.6.0.dist-info/WHEEL
mkdocs_test-0.6.0.dist-info/entry_points.txt
mkdocs_test-0.6.0.dist-info/top_level.txt
mkdocs_test-0.6.0.dist-info/RECORD
