Metadata-Version: 2.4
Name: mkdocs-test
Version: 0.6.0
Summary: A test framework for MkDocs projects
Author: Laurent Franceschetti
License: LICENSE
Project-URL: Source, https://github.com/fralau/mkdocs-test
Classifier: License :: OSI Approved :: MIT License
Classifier: Programming Language :: Python :: 3
Classifier: Programming Language :: Python :: 3.8
Classifier: Programming Language :: Python :: 3.9
Classifier: Programming Language :: Python :: 3.10
Classifier: Programming Language :: Python :: 3.11
Classifier: Programming Language :: Python :: 3.12
Requires-Python: >=3.8
License-File: LICENSE
Requires-Dist: beautifulsoup4
Requires-Dist: markdown
Requires-Dist: mkdocs
Requires-Dist: pandas
Requires-Dist: pyyaml
Requires-Dist: rich
Requires-Dist: super-collections
Requires-Dist: lxml
Provides-Extra: test
Requires-Dist: pytest>=7.0; extra == "test"
Requires-Dist: toml-cli; extra == "test"
Requires-Dist: mkdocs-test; extra == "test"
Provides-Extra: doc
Requires-Dist: mkdocs-alabaster; extra == "doc"
Requires-Dist: mkdocstrings[python]; extra == "doc"
Dynamic: license-file
